odoo/addons/ssi_revenue_recognition_project_operating_unit/README.rst
odoo/addons/ssi_revenue_recognition_project_operating_unit/__init__.py
odoo/addons/ssi_revenue_recognition_project_operating_unit/__manifest__.py
odoo/addons/ssi_revenue_recognition_project_operating_unit/models/__init__.py
odoo/addons/ssi_revenue_recognition_project_operating_unit/models/service_contract_performance_obligation.py
odoo/addons/ssi_revenue_recognition_project_operating_unit/static/description/banner.png
odoo/addons/ssi_revenue_recognition_project_operating_unit/static/description/icon.png
odoo14_addon_ssi_revenue_recognition_project_operating_unit-14.0.2.0.0.dist-info/METADATA
odoo14_addon_ssi_revenue_recognition_project_operating_unit-14.0.2.0.0.dist-info/WHEEL
odoo14_addon_ssi_revenue_recognition_project_operating_unit-14.0.2.0.0.dist-info/top_level.txt
odoo14_addon_ssi_revenue_recognition_project_operating_unit-14.0.2.0.0.dist-info/RECORD
